netbits/__init__.py
netbits/buffer.py
netbits/handler.py
netbits/packet.py
netbits/sockets.py
netbits/registries/__init__.py
netbits/registries/identifier.py
netbits/registries/registry.py
netbits-0.0.3.dist-info/COPYING
netbits-0.0.3.dist-info/COPYING.LESSER
netbits-0.0.3.dist-info/METADATA
netbits-0.0.3.dist-info/WHEEL
netbits-0.0.3.dist-info/top_level.txt
netbits-0.0.3.dist-info/RECORD
