Metadata-Version: 2.1
Name: netbits
Version: 0.0.3
Summary: Convert data into structured packets and make packet handling a breeze!
Author: Samuel Hulme
Project-URL: Homepage, https://github.com/ajh123/netbits
Project-URL: Issues, https://github.com/ajh123/netbits/issues
Project-URL: Documentation, https://netbits.minersonline.uk/en/latest/
Requires-Python: >=3.8
License-File: COPYING
License-File: COPYING.LESSER
